croud/__init__.py
croud/__main__.py
croud/api.py
croud/login.py
croud/logout.py
croud/me.py
croud/parser.py
croud/printer.py
croud/server.py
croud/typing.py
croud/util.py
croud/apikeys/__init__.py
croud/apikeys/commands.py
croud/cloud_configurations/__init__.py
croud/cloud_configurations/commands.py
croud/clusters/__init__.py
croud/clusters/commands.py
croud/clusters/exceptions.py
croud/config/__init__.py
croud/config/commands.py
croud/config/configuration.py
croud/config/exceptions.py
croud/config/schemas.py
croud/config/types.py
croud/config/util.py
croud/consumers/__init__.py
croud/organizations/__init__.py
croud/organizations/commands.py
croud/organizations/auditlogs/__init__.py
croud/organizations/auditlogs/commands.py
croud/organizations/users/__init__.py
croud/organizations/users/commands.py
croud/products/__init__.py
croud/products/commands.py
croud/projects/__init__.py
croud/projects/commands.py
croud/projects/users/__init__.py
croud/projects/users/commands.py
croud/regions/__init__.py
croud/regions/commands.py
croud/subscriptions/__init__.py
croud/subscriptions/commands.py
croud/tools/__init__.py
croud/tools/spinner.py
croud/users/__init__.py
croud/users/commands.py
croud/users/roles/__init__.py
croud/users/roles/commands.py
croud-1.15.0.dist-info/licenses/LICENSE
tests/__init__.py
tests/conftest.py
tests/test_api.py
tests/test_config_schemas.py
tests/test_configuration.py
tests/test_parser.py
tests/test_printer.py
tests/test_server.py
tests/test_util.py
tests/commands/__init__.py
tests/commands/test_api_keys.py
tests/commands/test_cloud_configurations.py
tests/commands/test_clusters.py
tests/commands/test_clusters_scheduled_jobs.py
tests/commands/test_config.py
tests/commands/test_login.py
tests/commands/test_logout.py
tests/commands/test_me.py
tests/commands/test_organizations.py
tests/commands/test_products.py
tests/commands/test_projects.py
tests/commands/test_regions.py
tests/commands/test_subscriptions.py
tests/commands/test_users.py
tests/util/__init__.py
tests/util/fake_cloud.py
croud-1.15.0.dist-info/METADATA
croud-1.15.0.dist-info/WHEEL
croud-1.15.0.dist-info/entry_points.txt
croud-1.15.0.dist-info/top_level.txt
croud-1.15.0.dist-info/RECORD
