Metadata-Version: 2.4
Name: croud
Version: 1.15.0
Summary: A command line interface for CrateDB Cloud
Home-page: https://github.com/crate/croud
Author: Crate.io
Author-email: office@crate.io
Classifier: Development Status :: 4 - Beta
Classifier: Intended Audience :: Developers
Classifier: License :: OSI Approved :: Apache Software License
Classifier: Operating System :: OS Independent
Classifier: Topic :: Database
Classifier: Programming Language :: Python :: 3
Classifier: Programming Language :: Python :: 3.9
Classifier: Programming Language :: Python :: 3.10
Classifier: Programming Language :: Python :: 3.11
Classifier: Programming Language :: Python :: 3.12
Classifier: Programming Language :: Python :: 3.13
Requires-Python: >=3.9
License-File: LICENSE
Requires-Dist: bitmath<2,>=1
Requires-Dist: certifi
Requires-Dist: colorama<1,>=0.3
Requires-Dist: importlib-metadata; python_version < "3.8"
Requires-Dist: marshmallow<4,>=3
Requires-Dist: platformdirs<5,>=4
Requires-Dist: pyyaml<7,>=6.0.2
Requires-Dist: requests<3,>=2
Requires-Dist: tabulate<1.0,>=0.8
Requires-Dist: yarl<2,>=1
Requires-Dist: halo<0.1
Requires-Dist: shtab<2,>=1
Requires-Dist: tqdm<5,>=4
Provides-Extra: testing
Requires-Dist: pytest<9; extra == "testing"
Requires-Dist: pytest-cov<7; extra == "testing"
Requires-Dist: pytest-freezer<0.5; extra == "testing"
Requires-Dist: pytest-mock<4; extra == "testing"
Requires-Dist: pytest-random-order<2; extra == "testing"
Requires-Dist: tox<4; extra == "testing"
Provides-Extra: development
Requires-Dist: black<26; extra == "development"
Requires-Dist: flake8<7.3; extra == "development"
Requires-Dist: isort<6; extra == "development"
Requires-Dist: mypy<1.18; extra == "development"
Dynamic: author
Dynamic: author-email
Dynamic: classifier
Dynamic: description
Dynamic: description-content-type
Dynamic: home-page
Dynamic: license-file
Dynamic: provides-extra
Dynamic: requires-dist
Dynamic: requires-python
Dynamic: summary
